{
"meta":{"test_sets":[],"test_metrics":[],"learn_metrics":[{"best_value":"Min","name":"Logloss"}],"launch_mode":"Train","parameters":"","iteration_count":200,"learn_sets":["learn"],"name":"experiment"},
"iterations":[
{"learn":[0.6414715069],"iteration":0,"passed_time":0.007617818885,"remaining_time":1.515945958},
{"learn":[0.5897173544],"iteration":1,"passed_time":0.01597839368,"remaining_time":1.581860975},
{"learn":[0.5576135196],"iteration":2,"passed_time":0.02335595689,"remaining_time":1.533707836},
{"learn":[0.5245553051],"iteration":3,"passed_time":0.03038082357,"remaining_time":1.488660355},
{"learn":[0.504866656],"iteration":4,"passed_time":0.03838104992,"remaining_time":1.496860947},
{"learn":[0.48211321],"iteration":5,"passed_time":0.0464938387,"remaining_time":1.503300785},
{"learn":[0.4666344215],"iteration":6,"passed_time":0.05152623449,"remaining_time":1.420651894},
{"learn":[0.4432705586],"iteration":7,"passed_time":0.05712155595,"remaining_time":1.370917343},
{"learn":[0.4241401731],"iteration":8,"passed_time":0.06312625827,"remaining_time":1.339679481},
{"learn":[0.4094465753],"iteration":9,"passed_time":0.06896373569,"remaining_time":1.310310978},
{"learn":[0.3947040518],"iteration":10,"passed_time":0.07539110249,"remaining_time":1.295356216},
{"learn":[0.3851820621],"iteration":11,"passed_time":0.08106624268,"remaining_time":1.270037802},
{"learn":[0.3680709189],"iteration":12,"passed_time":0.08631600654,"remaining_time":1.241622556},
{"learn":[0.3546043209],"iteration":13,"passed_time":0.09304137803,"remaining_time":1.236121165},
{"learn":[0.3382709101],"iteration":14,"passed_time":0.09810701514,"remaining_time":1.20998652},
{"learn":[0.3250368019],"iteration":15,"passed_time":0.104619256,"remaining_time":1.203121443},
{"learn":[0.315501789],"iteration":16,"passed_time":0.1105503918,"remaining_time":1.190042453},
{"learn":[0.3073458365],"iteration":17,"passed_time":0.1160261585,"remaining_time":1.173153381},
{"learn":[0.293892347],"iteration":18,"passed_time":0.1219702407,"remaining_time":1.16192703},
{"learn":[0.2828936],"iteration":19,"passed_time":0.1274100579,"remaining_time":1.146690521},
{"learn":[0.2756567386],"iteration":20,"passed_time":0.1325289859,"remaining_time":1.129651832},
{"learn":[0.2687468529],"iteration":21,"passed_time":0.1388646984,"remaining_time":1.123541651},
{"learn":[0.2591119508],"iteration":22,"passed_time":0.1440307588,"remaining_time":1.108410622},
{"learn":[0.2529230376],"iteration":23,"passed_time":0.1493202103,"remaining_time":1.095014876},
{"learn":[0.2458877997],"iteration":24,"passed_time":0.1559954897,"remaining_time":1.091968428},
{"learn":[0.2383706422],"iteration":25,"passed_time":0.1612635885,"remaining_time":1.079225554},
{"learn":[0.2331885138],"iteration":26,"passed_time":0.1664934474,"remaining_time":1.066791348},
{"learn":[0.2281785313],"iteration":27,"passed_time":0.1721614547,"remaining_time":1.057563222},
{"learn":[0.2240049045],"iteration":28,"passed_time":0.1777457228,"remaining_time":1.048086848},
{"learn":[0.2167594345],"iteration":29,"passed_time":0.1834554742,"remaining_time":1.039581021},
{"learn":[0.2096262907],"iteration":30,"passed_time":0.1890821898,"remaining_time":1.030802906},
{"learn":[0.2045769406],"iteration":31,"passed_time":0.1961433249,"remaining_time":1.029752456},
{"learn":[0.1993411651],"iteration":32,"passed_time":0.2054437698,"remaining_time":1.039669986},
{"learn":[0.1967287215],"iteration":33,"passed_time":0.2107046742,"remaining_time":1.028734586},
{"learn":[0.1935503551],"iteration":34,"passed_time":0.2162634881,"remaining_time":1.019527873},
{"learn":[0.1905783935],"iteration":35,"passed_time":0.2225497678,"remaining_time":1.013837831},
{"learn":[0.1858355908],"iteration":36,"passed_time":0.2279106854,"remaining_time":1.004038966},
{"learn":[0.1823625662],"iteration":37,"passed_time":0.2347512397,"remaining_time":1.000781601},
{"learn":[0.1769441296],"iteration":38,"passed_time":0.2409408973,"remaining_time":0.9946534479},
{"learn":[0.1728184218],"iteration":39,"passed_time":0.2480556846,"remaining_time":0.9922227385},
{"learn":[0.1694428615],"iteration":40,"passed_time":0.2534533045,"remaining_time":0.9829042783},
{"learn":[0.1657739995],"iteration":41,"passed_time":0.258616275,"remaining_time":0.9728897964},
{"learn":[0.1627023839],"iteration":42,"passed_time":0.2644882441,"remaining_time":0.9656896355},
{"learn":[0.1597700757],"iteration":43,"passed_time":0.2700106166,"remaining_time":0.957310368},
{"learn":[0.1568477267],"iteration":44,"passed_time":0.2752749482,"remaining_time":0.9481692662},
{"learn":[0.1539228924],"iteration":45,"passed_time":0.2831515414,"remaining_time":0.9479421169},
{"learn":[0.150884321],"iteration":46,"passed_time":0.2883213196,"remaining_time":0.9385779127},
{"learn":[0.1466385581],"iteration":47,"passed_time":0.2932619442,"remaining_time":0.9286628233},
{"learn":[0.1452191695],"iteration":48,"passed_time":0.2996249885,"remaining_time":0.9233341482},
{"learn":[0.1421801758],"iteration":49,"passed_time":0.3048765204,"remaining_time":0.9146295611},
{"learn":[0.1384874248],"iteration":50,"passed_time":0.3112006716,"remaining_time":0.9091941189},
{"learn":[0.1348230056],"iteration":51,"passed_time":0.3166863315,"remaining_time":0.9013380203},
{"learn":[0.1323698954],"iteration":52,"passed_time":0.3218247018,"remaining_time":0.8926081351},
{"learn":[0.1301843019],"iteration":53,"passed_time":0.3284163452,"remaining_time":0.8879404889},
{"learn":[0.1281071512],"iteration":54,"passed_time":0.3343418009,"remaining_time":0.881446566},
{"learn":[0.1261666545],"iteration":55,"passed_time":0.3394878472,"remaining_time":0.8729687499},
{"learn":[0.1236144561],"iteration":56,"passed_time":0.3462014489,"remaining_time":0.8685404771},
{"learn":[0.1212931111],"iteration":57,"passed_time":0.351121645,"remaining_time":0.859642648},
{"learn":[0.1197409961],"iteration":58,"passed_time":0.357146873,"remaining_time":0.8535204932},
{"learn":[0.1175645142],"iteration":59,"passed_time":0.3627984243,"remaining_time":0.8465296567},
{"learn":[0.1155197883],"iteration":60,"passed_time":0.3682430797,"remaining_time":0.8391112801},
{"learn":[0.1129875855],"iteration":61,"passed_time":0.3767328797,"remaining_time":0.8385344742},
{"learn":[0.111053484],"iteration":62,"passed_time":0.3858510093,"remaining_time":0.8390728297},
{"learn":[0.1088450423],"iteration":63,"passed_time":0.3945519194,"remaining_time":0.8384228287},
{"learn":[0.1059701612],"iteration":64,"passed_time":0.4002262183,"remaining_time":0.8312390688},
{"learn":[0.1043827907],"iteration":65,"passed_time":0.4066374267,"remaining_time":0.8255971996},
{"learn":[0.1022558501],"iteration":66,"passed_time":0.4113857086,"remaining_time":0.8166313319},
{"learn":[0.1003051941],"iteration":67,"passed_time":0.4173941864,"remaining_time":0.8102357736},
{"learn":[0.09808509194],"iteration":68,"passed_time":0.4243906429,"remaining_time":0.8057271627},
{"learn":[0.09648127874],"iteration":69,"passed_time":0.4298834959,"remaining_time":0.7983550638},
{"learn":[0.09532606862],"iteration":70,"passed_time":0.4357587122,"remaining_time":0.7917306179},
{"learn":[0.09385000295],"iteration":71,"passed_time":0.441761242,"remaining_time":0.7853533192},
{"learn":[0.09179111787],"iteration":72,"passed_time":0.4474406443,"remaining_time":0.7784241347},
{"learn":[0.09050138185],"iteration":73,"passed_time":0.4539846767,"remaining_time":0.773000936},
{"learn":[0.08930424773],"iteration":74,"passed_time":0.4600717803,"remaining_time":0.7667863006},
{"learn":[0.0877145688],"iteration":75,"passed_time":0.4648592442,"remaining_time":0.7584545563},
{"learn":[0.0859978696],"iteration":76,"passed_time":0.4733282479,"remaining_time":0.7560957726},
{"learn":[0.08460040866],"iteration":77,"passed_time":0.4786356836,"remaining_time":0.7486353},
{"learn":[0.08244818303],"iteration":78,"passed_time":0.4852311276,"remaining_time":0.7432021068},
{"learn":[0.08054437364],"iteration":79,"passed_time":0.4912699499,"remaining_time":0.7369049249},
{"learn":[0.07845869928],"iteration":80,"passed_time":0.4968725426,"remaining_time":0.7299732415},
{"learn":[0.07707589524],"iteration":81,"passed_time":0.5040050553,"remaining_time":0.7252755674},
{"learn":[0.07590369373],"iteration":82,"passed_time":0.5094175892,"remaining_time":0.718094674},
{"learn":[0.0745844932],"iteration":83,"passed_time":0.5152995728,"remaining_time":0.7116041719},
{"learn":[0.07329259679],"iteration":84,"passed_time":0.5229555877,"remaining_time":0.7075281481},
{"learn":[0.07195677809],"iteration":85,"passed_time":0.5287320155,"remaining_time":0.7008773229},
{"learn":[0.07074354942],"iteration":86,"passed_time":0.5361409238,"remaining_time":0.696366947},
{"learn":[0.06996695125],"iteration":87,"passed_time":0.5417935591,"remaining_time":0.6895554389},
{"learn":[0.06873036893],"iteration":88,"passed_time":0.5470447584,"remaining_time":0.6822693054},
{"learn":[0.067369107],"iteration":89,"passed_time":0.5553202164,"remaining_time":0.6787247089},
{"learn":[0.06598316291],"iteration":90,"passed_time":0.5626282024,"remaining_time":0.6739172973},
{"learn":[0.06481926643],"iteration":91,"passed_time":0.5702172765,"remaining_time":0.6693854985},
{"learn":[0.0637925886],"iteration":92,"passed_time":0.5755081781,"remaining_time":0.6621438178},
{"learn":[0.06231719272],"iteration":93,"passed_time":0.5854567355,"remaining_time":0.6601958933},
{"learn":[0.0615187211],"iteration":94,"passed_time":0.591310148,"remaining_time":0.6535533215},
{"learn":[0.06068807304],"iteration":95,"passed_time":0.5971437247,"remaining_time":0.6469057017},
{"learn":[0.06001318281],"iteration":96,"passed_time":0.6034883275,"remaining_time":0.6408175024},
{"learn":[0.05893753822],"iteration":97,"passed_time":0.6096068142,"remaining_time":0.634488725},
{"learn":[0.05780217043],"iteration":98,"passed_time":0.617123445,"remaining_time":0.6295905853},
{"learn":[0.05673624319],"iteration":99,"passed_time":0.6223595695,"remaining_time":0.6223595695},
{"learn":[0.05582256246],"iteration":100,"passed_time":0.6286837381,"remaining_time":0.6162345552},
{"learn":[0.05458814831],"iteration":101,"passed_time":0.6339201081,"remaining_time":0.609060496},
{"learn":[0.05362788728],"iteration":102,"passed_time":0.6390651318,"remaining_time":0.6018380367},
{"learn":[0.05272762067],"iteration":103,"passed_time":0.6451985389,"remaining_time":0.5955678821},
{"learn":[0.05198281695],"iteration":104,"passed_time":0.650553413,"remaining_time":0.5885959451},
{"learn":[0.05150110683],"iteration":105,"passed_time":0.6559107381,"remaining_time":0.5816566923},
{"learn":[0.05052252329],"iteration":106,"passed_time":0.6631407663,"remaining_time":0.5763746847},
{"learn":[0.0496295801],"iteration":107,"passed_time":0.668262916,"remaining_time":0.5692610026},
{"learn":[0.04867593307],"iteration":108,"passed_time":0.673701163,"remaining_time":0.5624477599},
{"learn":[0.04794141804],"iteration":109,"passed_time":0.6804860418,"remaining_time":0.5567613069},
{"learn":[0.04721988287],"iteration":110,"passed_time":0.6854536442,"remaining_time":0.5495979669},
{"learn":[0.04618212573],"iteration":111,"passed_time":0.6907639123,"remaining_time":0.5427430739},
{"learn":[0.04541785678],"iteration":112,"passed_time":0.6974630308,"remaining_time":0.5369848113},
{"learn":[0.04460623998],"iteration":113,"passed_time":0.7032219285,"remaining_time":0.5305007531},
{"learn":[0.0439505353],"iteration":114,"passed_time":0.7095080546,"remaining_time":0.5244189969},
{"learn":[0.0434383966],"iteration":115,"passed_time":0.7148663512,"remaining_time":0.5176618405},
{"learn":[0.04263107069],"iteration":116,"passed_time":0.7198805036,"remaining_time":0.5106844598},
{"learn":[0.04197537607],"iteration":117,"passed_time":0.7261267697,"remaining_time":0.5045965688},
{"learn":[0.04128739165],"iteration":118,"passed_time":0.7326762768,"remaining_time":0.4987124237},
{"learn":[0.04067055503],"iteration":119,"passed_time":0.7407862018,"remaining_time":0.4938574679},
{"learn":[0.04001336397],"iteration":120,"passed_time":0.7481763904,"remaining_time":0.4884788004},
{"learn":[0.03938693669],"iteration":121,"passed_time":0.7802177088,"remaining_time":0.4988277155},
{"learn":[0.03878308252],"iteration":122,"passed_time":0.7911014257,"remaining_time":0.4952423559},
{"learn":[0.03809547099],"iteration":123,"passed_time":0.7987716818,"remaining_time":0.4895697405},
{"learn":[0.03764137325],"iteration":124,"passed_time":0.807496607,"remaining_time":0.4844979642},
{"learn":[0.03725115642],"iteration":125,"passed_time":0.8144241724,"remaining_time":0.4783126092},
{"learn":[0.03685012468],"iteration":126,"passed_time":0.8219768348,"remaining_time":0.4724748735},
{"learn":[0.03649139307],"iteration":127,"passed_time":0.8299445716,"remaining_time":0.4668438215},
{"learn":[0.03589902327],"iteration":128,"passed_time":0.8376473176,"remaining_time":0.4610306942},
{"learn":[0.0353691854],"iteration":129,"passed_time":0.8463508971,"remaining_time":0.4557274061},
{"learn":[0.03509218069],"iteration":130,"passed_time":0.8553264588,"remaining_time":0.450515463},
{"learn":[0.03462832403],"iteration":131,"passed_time":0.8641028837,"remaining_time":0.4451439098},
{"learn":[0.03387331021],"iteration":132,"passed_time":0.8741553675,"remaining_time":0.4403639821},
{"learn":[0.03338330838],"iteration":133,"passed_time":0.8837685869,"remaining_time":0.4352890055},
{"learn":[0.03304363044],"iteration":134,"passed_time":0.8959161694,"remaining_time":0.4313670445},
{"learn":[0.03269299369],"iteration":135,"passed_time":0.9051003802,"remaining_time":0.4259295907},
{"learn":[0.03234392876],"iteration":136,"passed_time":0.9144339321,"remaining_time":0.4205061148},
{"learn":[0.0320020625],"iteration":137,"passed_time":0.925133197,"remaining_time":0.4156395523},
{"learn":[0.03149526386],"iteration":138,"passed_time":0.9328231473,"remaining_time":0.4093684316},
{"learn":[0.03095559593],"iteration":139,"passed_time":0.9398917677,"remaining_time":0.4028107576},
{"learn":[0.03064546663],"iteration":140,"passed_time":0.9470361193,"remaining_time":0.3962775251},
{"learn":[0.03029128641],"iteration":141,"passed_time":0.9554162891,"remaining_time":0.3902404561},
{"learn":[0.03010874548],"iteration":142,"passed_time":0.9626795091,"remaining_time":0.3837253987},
{"learn":[0.02975242339],"iteration":143,"passed_time":0.9706028674,"remaining_time":0.3774566707},
{"learn":[0.02928047024],"iteration":144,"passed_time":0.9775940472,"remaining_time":0.3708115352},
{"learn":[0.02891446524],"iteration":145,"passed_time":0.9862484113,"remaining_time":0.3647768097},
{"learn":[0.02860465816],"iteration":146,"passed_time":0.9933673278,"remaining_time":0.3581528461},
{"learn":[0.02811035343],"iteration":147,"passed_time":1.001201932,"remaining_time":0.3517736519},
{"learn":[0.02782464287],"iteration":148,"passed_time":1.008013276,"remaining_time":0.3450246782},
{"learn":[0.02757936343],"iteration":149,"passed_time":1.015656759,"remaining_time":0.3385522529},
{"learn":[0.02738671082],"iteration":150,"passed_time":1.023482019,"remaining_time":0.3321233041},
{"learn":[0.02700988733],"iteration":151,"passed_time":1.031063105,"remaining_time":0.3255988753},
{"learn":[0.02672586194],"iteration":152,"passed_time":1.037163207,"remaining_time":0.3186056911},
{"learn":[0.02643718966],"iteration":153,"passed_time":1.044413903,"remaining_time":0.3119677892},
{"learn":[0.02615552962],"iteration":154,"passed_time":1.050727362,"remaining_time":0.3050498794},
{"learn":[0.02582443573],"iteration":155,"passed_time":1.058035678,"remaining_time":0.2984203194},
{"learn":[0.02548283257],"iteration":156,"passed_time":1.066229275,"remaining_time":0.2920245784},
{"learn":[0.02523416135],"iteration":157,"passed_time":1.073026959,"remaining_time":0.2852350145},
{"learn":[0.02505057839],"iteration":158,"passed_time":1.081316455,"remaining_time":0.2788300293},
{"learn":[0.02481886866],"iteration":159,"passed_time":1.090130274,"remaining_time":0.2725325686},
{"learn":[0.02462779469],"iteration":160,"passed_time":1.100388152,"remaining_time":0.2665536517},
{"learn":[0.02435507047],"iteration":161,"passed_time":1.148776338,"remaining_time":0.2694660546},
{"learn":[0.02408044215],"iteration":162,"passed_time":1.169392639,"remaining_time":0.2654449549},
{"learn":[0.02376711206],"iteration":163,"passed_time":1.177948876,"remaining_time":0.2585741436},
{"learn":[0.02342749292],"iteration":164,"passed_time":1.185212125,"remaining_time":0.2514086325},
{"learn":[0.02321444545],"iteration":165,"passed_time":1.196271251,"remaining_time":0.2450194129},
{"learn":[0.02300247185],"iteration":166,"passed_time":1.204770982,"remaining_time":0.2380685173},
{"learn":[0.02269278755],"iteration":167,"passed_time":1.213196163,"remaining_time":0.2310849835},
{"learn":[0.02243207911],"iteration":168,"passed_time":1.22287886,"remaining_time":0.2243150571},
{"learn":[0.02227111473],"iteration":169,"passed_time":1.231253377,"remaining_time":0.2172800077},
{"learn":[0.02209861532],"iteration":170,"passed_time":1.240113606,"remaining_time":0.2103116641},
{"learn":[0.02186894547],"iteration":171,"passed_time":1.246314285,"remaining_time":0.202888372},
{"learn":[0.02163012021],"iteration":172,"passed_time":1.254563852,"remaining_time":0.1957989827},
{"learn":[0.02137527999],"iteration":173,"passed_time":1.261613169,"remaining_time":0.1885169103},
{"learn":[0.02123491706],"iteration":174,"passed_time":1.267951813,"remaining_time":0.1811359734},
{"learn":[0.02101942954],"iteration":175,"passed_time":1.274813581,"remaining_time":0.1738382156},
{"learn":[0.02086962926],"iteration":176,"passed_time":1.281575749,"remaining_time":0.1665324419},
{"learn":[0.0206171076],"iteration":177,"passed_time":1.290392105,"remaining_time":0.1594866647},
{"learn":[0.02041913378],"iteration":178,"passed_time":1.297789449,"remaining_time":0.152254628},
{"learn":[0.02025475099],"iteration":179,"passed_time":1.30521811,"remaining_time":0.1450242344},
{"learn":[0.02010630652],"iteration":180,"passed_time":1.311153136,"remaining_time":0.1376348596},
{"learn":[0.01992303669],"iteration":181,"passed_time":1.318500281,"remaining_time":0.1304011267},
{"learn":[0.01975813159],"iteration":182,"passed_time":1.32526758,"remaining_time":0.1231122889},
{"learn":[0.01959653576],"iteration":183,"passed_time":1.332026645,"remaining_time":0.1158284039},
{"learn":[0.01946176755],"iteration":184,"passed_time":1.338916421,"remaining_time":0.1085607909},
{"learn":[0.01931338804],"iteration":185,"passed_time":1.345259105,"remaining_time":0.1012560617},
{"learn":[0.0192015275],"iteration":186,"passed_time":1.352882954,"remaining_time":0.09405068666},
{"learn":[0.01909084996],"iteration":187,"passed_time":1.360055069,"remaining_time":0.08681202566},
{"learn":[0.01897702035],"iteration":188,"passed_time":1.36909955,"remaining_time":0.07968304257},
{"learn":[0.01893284925],"iteration":189,"passed_time":1.376794955,"remaining_time":0.07246289239},
{"learn":[0.01877866714],"iteration":190,"passed_time":1.383887415,"remaining_time":0.06520935466},
{"learn":[0.01862084443],"iteration":191,"passed_time":1.390333953,"remaining_time":0.05793058138},
{"learn":[0.01842469351],"iteration":192,"passed_time":1.397937835,"remaining_time":0.05070240853},
{"learn":[0.01827082452],"iteration":193,"passed_time":1.40529219,"remaining_time":0.04346264506},
{"learn":[0.01814218373],"iteration":194,"passed_time":1.410902753,"remaining_time":0.03617699367},
{"learn":[0.01798083737],"iteration":195,"passed_time":1.418163811,"remaining_time":0.0289421186},
{"learn":[0.0178069789],"iteration":196,"passed_time":1.426167728,"remaining_time":0.02171829028},
{"learn":[0.01766237251],"iteration":197,"passed_time":1.433414931,"remaining_time":0.0144789387},
{"learn":[0.01757861938],"iteration":198,"passed_time":1.438992095,"remaining_time":0.007231116057},
{"learn":[0.01747870445],"iteration":199,"passed_time":1.447494137,"remaining_time":0}
]}